[
  {
    "title": "Какое ты время года?",
    "result_names": [
      "Осень",
      "Зима",
      "Весна"
    ],
    "questions": [
      {
        "text": "Какое время года ты любишь?",
        "options": [
          {
            "text": "Осень",
            "result_index": 0
          },
          {
            "text": "Зима",
            "result_index": 1
          },
          {
            "text": "Весна",
            "result_index": 2
          }
        ]
      }
    ],
    "author": "Доброе утро"
  },
  {
    "title": "Ты Человек-Паук или Зелёный Гоблин?",
    "result_names": [
      "Человек-Паук",
      "Зелёный Гоблин"
    ],
    "questions": [
      {
        "text": "Мы не так уж с тобой и отличаемся, Человек-Паук...",
        "options": [
          {
            "text": "Нет",
            "result_index": 0
          },
          {
            "text": "Да",
            "result_index": 1
          }
        ]
      }
    ],
    "author": "Зелёный Гоблин"
  },
  {
    "title": "Какой ты супергерой?",
    "result_names": [
      "Супермен",
      "Бэтмен",
      "Человек-Паук"
    ],
    "questions": [
      {
        "text": "Противник атакует! Что ты сделаешь?",
        "options": [
          {
            "text": "Испепелю его своими глазами",
            "result_index": 0
          },
          {
            "text": "Сломаю все кости в его теле",
            "result_index": 1
          },
          {
            "text": "Увернусь от удара",
            "result_index": 2
          }
        ]
      },
      {
        "text": "Что ты ценишь больше?",
        "options": [
          {
            "text": "Справедливость",
            "result_index": 0
          },
          {
            "text": "Родителей",
            "result_index": 1
          },
          {
            "text": "Мэри Джейн",
            "result_index": 2
          }
        ]
      },
      {
        "text": "Как ты относишься к командной работе?",
        "options": [
          {
            "text": "Я прирожденный лидер",
            "result_index": 0
          },
          {
            "text": "Я работаю один",
            "result_index": 1
          },
          {
            "text": "Люблю поболтать с напарниками",
            "result_index": 2
          }
        ]
      }
    ],
    "author": "Новый пользователь"
  }
]